h2cow/__init__.py
h2cow/__main__.py
h2cow/_version.py
h2cow/cli.py
h2cow/analysis/__init__.py
h2cow/analysis/identification.py
h2cow/analysis/pose_estimation.py
h2cow/create_project/__init__.py
h2cow/create_project/new_project.py
h2cow/data_collection/__init__.py
h2cow/data_collection/__keep_until_used.py
h2cow/data_collection/data_collection.py
h2cow/data_collection/stream_reader.py
h2cow/data_collection/water_meter.py
h2cow/utils/__init__.py
h2cow/utils/configure.py
h2cow-1.0.12.dist-info/LICENSE
h2cow-1.0.12.dist-info/METADATA
h2cow-1.0.12.dist-info/WHEEL
h2cow-1.0.12.dist-info/entry_points.txt
h2cow-1.0.12.dist-info/top_level.txt
h2cow-1.0.12.dist-info/RECORD
