Metadata-Version: 2.1
Name: h2cow
Version: 1.0.12
Summary: Monitoring drinking behaviour of animals.
Home-page: https://github.com/danielvh8/Master-Research-Project-2022
Author: Daniël M. van Herwijnen
Author-email: danielvh8@gmail.com
License: MIT
Requires-Python: ==3.10.4
License-File: LICENSE
Requires-Dist: click (==8.1.3)
Requires-Dist: deeplabcut (==2.2.2)
Requires-Dist: numpy (>=1.18.5)
Requires-Dist: opencv-contrib-python (==4.6.0.66)
Requires-Dist: ruamel.yaml (>=0.15.0)
Requires-Dist: setuptools (<60)
